LICENSE-MIT
README.rst
setup.py
src/djazator/__init__.py
src/djazator/mq.py
src/djazator/pub.py
src/djazator/server.py
src/djazator/sub.py
src/djazator/utils.py
src/djazator.egg-info/PKG-INFO
src/djazator.egg-info/SOURCES.txt
src/djazator.egg-info/dependency_links.txt
src/djazator.egg-info/entry_points.txt
src/djazator.egg-info/requires.txt
src/djazator.egg-info/top_level.txt
src/djazator/templatetags/__init__.py
src/djazator/templatetags/djazator.py