Metadata-Version: 1.1
Name: djazator
Version: 0.2.4
Summary: A simple django plugin for sending push notifications from django server to sockjs clients
Home-page: UNKNOWN
Author: Mike Oskin
Author-email: cheap.grayhat@gmail.com
License: MIT
Keywords: django zeromq tornado sockjs
Platform: UNKNOWN
Classifier: License :: OSI Approved :: MIT License
Classifier: Framework :: Django
